dvg/__init__.py
dvg/__main__.py
dvg/dvg.py
dvg/dvgi.py
dvg/iter_funcs.py
dvg/models.py
dvg/scanners.py
dvg/scdv_embedding.py
dvg/search_result.py
dvg/text_funcs.py
dvg/util.py
dvg/bin/placeholder.txt
dvg/models/model-urls.txt
tests/__init__.py
tests/test_dvg_util_funcs.py
tests/test_iter_funcs.py
tests/test_models.py
tests/test_scanners.py
tests/test_scdv_embedding.py
tests/test_text_funcs.py
dvg-1.0.0b11.dist-info/LICENSE
dvg-1.0.0b11.dist-info/METADATA
dvg-1.0.0b11.dist-info/WHEEL
dvg-1.0.0b11.dist-info/entry_points.txt
dvg-1.0.0b11.dist-info/top_level.txt
dvg-1.0.0b11.dist-info/RECORD
